{"nodes": [{"id": "users_hichem_desktop_shopnotify_src_shopify_js", "label": "shopify.js", "file_type": "code", "source_file": "/Users/hichem/Desktop/shopnotify/src/shopify.js", "source_location": "L1"}, {"id": "shopify_verifywebhook", "label": "verifyWebhook()", "file_type": "code", "source_file": "/Users/hichem/Desktop/shopnotify/src/shopify.js", "source_location": "L6"}, {"id": "shopify_handleshopifywebhook", "label": "handleShopifyWebhook()", "file_type": "code", "source_file": "/Users/hichem/Desktop/shopnotify/src/shopify.js", "source_location": "L21"}, {"id": "shopify_formataddress", "label": "formatAddress()", "file_type": "code", "source_file": "/Users/hichem/Desktop/shopnotify/src/shopify.js", "source_location": "L89"}], "edges": [{"source": "users_hichem_desktop_shopnotify_src_shopify_js", "target": "shopify_verifywebhook", "relation": "contains", "confidence": "EXTRACTED", "source_file": "/Users/hichem/Desktop/shopnotify/src/shopify.js", "source_location": "L6", "weight": 1.0}, {"source": "users_hichem_desktop_shopnotify_src_shopify_js", "target": "shopify_handleshopifywebhook", "relation": "contains", "confidence": "EXTRACTED", "source_file": "/Users/hichem/Desktop/shopnotify/src/shopify.js", "source_location": "L21", "weight": 1.0}, {"source": "users_hichem_desktop_shopnotify_src_shopify_js", "target": "shopify_formataddress", "relation": "contains", "confidence": "EXTRACTED", "source_file": "/Users/hichem/Desktop/shopnotify/src/shopify.js", "source_location": "L89", "weight": 1.0}, {"source": "shopify_handleshopifywebhook", "target": "shopify_verifywebhook", "relation": "calls", "confidence": "EXTRACTED", "source_file": "/Users/hichem/Desktop/shopnotify/src/shopify.js", "source_location": "L23", "weight": 1.0}, {"source": "shopify_handleshopifywebhook", "target": "shopify_formataddress", "relation": "calls", "confidence": "EXTRACTED", "source_file": "/Users/hichem/Desktop/shopnotify/src/shopify.js", "source_location": "L66", "weight": 1.0}], "raw_calls": [{"caller_nid": "shopify_verifywebhook", "callee": "digest", "source_file": "/Users/hichem/Desktop/shopnotify/src/shopify.js", "source_location": "L12"}, {"caller_nid": "shopify_verifywebhook", "callee": "update", "source_file": "/Users/hichem/Desktop/shopnotify/src/shopify.js", "source_location": "L12"}, {"caller_nid": "shopify_verifywebhook", "callee": "createHmac", "source_file": "/Users/hichem/Desktop/shopnotify/src/shopify.js", "source_location": "L12"}, {"caller_nid": "shopify_verifywebhook", "callee": "timingSafeEqual", "source_file": "/Users/hichem/Desktop/shopnotify/src/shopify.js", "source_location": "L17"}, {"caller_nid": "shopify_verifywebhook", "callee": "from", "source_file": "/Users/hichem/Desktop/shopnotify/src/shopify.js", "source_location": "L17"}, {"caller_nid": "shopify_verifywebhook", "callee": "from", "source_file": "/Users/hichem/Desktop/shopnotify/src/shopify.js", "source_location": "L17"}, {"caller_nid": "shopify_handleshopifywebhook", "callee": "warn", "source_file": "/Users/hichem/Desktop/shopnotify/src/shopify.js", "source_location": "L24"}, {"caller_nid": "shopify_handleshopifywebhook", "callee": "json", "source_file": "/Users/hichem/Desktop/shopnotify/src/shopify.js", "source_location": "L25"}, {"caller_nid": "shopify_handleshopifywebhook", "callee": "status", "source_file": "/Users/hichem/Desktop/shopnotify/src/shopify.js", "source_location": "L25"}, {"caller_nid": "shopify_handleshopifywebhook", "callee": "json", "source_file": "/Users/hichem/Desktop/shopnotify/src/shopify.js", "source_location": "L29"}, {"caller_nid": "shopify_handleshopifywebhook", "callee": "status", "source_file": "/Users/hichem/Desktop/shopnotify/src/shopify.js", "source_location": "L29"}, {"caller_nid": "shopify_handleshopifywebhook", "callee": "parse", "source_file": "/Users/hichem/Desktop/shopnotify/src/shopify.js", "source_location": "L33"}, {"caller_nid": "shopify_handleshopifywebhook", "callee": "toString", "source_file": "/Users/hichem/Desktop/shopnotify/src/shopify.js", "source_location": "L33"}, {"caller_nid": "shopify_handleshopifywebhook", "callee": "error", "source_file": "/Users/hichem/Desktop/shopnotify/src/shopify.js", "source_location": "L35"}, {"caller_nid": "shopify_handleshopifywebhook", "callee": "log", "source_file": "/Users/hichem/Desktop/shopnotify/src/shopify.js", "source_location": "L39"}, {"caller_nid": "shopify_handleshopifywebhook", "callee": "warn", "source_file": "/Users/hichem/Desktop/shopnotify/src/shopify.js", "source_location": "L49"}, {"caller_nid": "shopify_handleshopifywebhook", "callee": "detectLanguage", "source_file": "/Users/hichem/Desktop/shopnotify/src/shopify.js", "source_location": "L54"}, {"caller_nid": "shopify_handleshopifywebhook", "callee": "trim", "source_file": "/Users/hichem/Desktop/shopnotify/src/shopify.js", "source_location": "L61"}, {"caller_nid": "shopify_handleshopifywebhook", "callee": "toFixed", "source_file": "/Users/hichem/Desktop/shopnotify/src/shopify.js", "source_location": "L64"}, {"caller_nid": "shopify_handleshopifywebhook", "callee": "parseFloat", "source_file": "/Users/hichem/Desktop/shopnotify/src/shopify.js", "source_location": "L64"}, {"caller_nid": "shopify_handleshopifywebhook", "callee": "map", "source_file": "/Users/hichem/Desktop/shopnotify/src/shopify.js", "source_location": "L67"}, {"caller_nid": "shopify_handleshopifywebhook", "callee": "toISOString", "source_file": "/Users/hichem/Desktop/shopnotify/src/shopify.js", "source_location": "L75"}, {"caller_nid": "shopify_handleshopifywebhook", "callee": "addOrder", "source_file": "/Users/hichem/Desktop/shopnotify/src/shopify.js", "source_location": "L78"}, {"caller_nid": "shopify_handleshopifywebhook", "callee": "require", "source_file": "/Users/hichem/Desktop/shopnotify/src/shopify.js", "source_location": "L82"}, {"caller_nid": "shopify_handleshopifywebhook", "callee": "sendConfirmation", "source_file": "/Users/hichem/Desktop/shopnotify/src/shopify.js", "source_location": "L83"}, {"caller_nid": "shopify_handleshopifywebhook", "callee": "error", "source_file": "/Users/hichem/Desktop/shopnotify/src/shopify.js", "source_location": "L85"}, {"caller_nid": "shopify_formataddress", "callee": "join", "source_file": "/Users/hichem/Desktop/shopnotify/src/shopify.js", "source_location": "L91"}, {"caller_nid": "shopify_formataddress", "callee": "filter", "source_file": "/Users/hichem/Desktop/shopnotify/src/shopify.js", "source_location": "L91"}]}